Metadata-Version: 2.1
Name: code-tracker
Version: 1.0.0
Author: None
Author-email: 
License: GPL-3
